Metadata-Version: 2.1
Name: nincore
Version: 0.0.1
Summary: Core utilities nin's packages.
Author: Ninnart Fuengfusin
Author-email: ninnart.fuengfusin@yahoo.com
License: Apache License 2.0
Requires-Python: >=3.6
License-File: LICENSE
